odoo/addons/footer_extra_info_account_move/README.rst
odoo/addons/footer_extra_info_account_move/__init__.py
odoo/addons/footer_extra_info_account_move/__manifest__.py
odoo/addons/footer_extra_info_account_move/models/__init__.py
odoo/addons/footer_extra_info_account_move/models/account_fiscal_position.py
odoo/addons/footer_extra_info_account_move/models/account_move.py
odoo/addons/footer_extra_info_account_move/readme/CONFIGURE.md
odoo/addons/footer_extra_info_account_move/readme/CONTRIBUTORS.md
odoo/addons/footer_extra_info_account_move/readme/DESCRIPTION.md
odoo/addons/footer_extra_info_account_move/static/description/icon.png
odoo/addons/footer_extra_info_account_move/static/description/index.html
odoo/addons/footer_extra_info_account_move/tests/__init__.py
odoo/addons/footer_extra_info_account_move/tests/test_footer_extra_info_account_move.py
odoo/addons/footer_extra_info_account_move/views/account_fiscal_position_views.xml
odoo_addon_footer_extra_info_account_move-16.0.1.0.0.1.dist-info/METADATA
odoo_addon_footer_extra_info_account_move-16.0.1.0.0.1.dist-info/WHEEL
odoo_addon_footer_extra_info_account_move-16.0.1.0.0.1.dist-info/top_level.txt
odoo_addon_footer_extra_info_account_move-16.0.1.0.0.1.dist-info/RECORD
