Metadata-Version: 2.1
Name: odoo-addon-footer_extra_info_account_move
Version: 16.0.1.0.0.1
Requires-Python: >=3.10
Requires-Dist: odoo-addon-footer_extra_info_base>=16.0dev,<16.1dev
Requires-Dist: odoo>=16.0a,<16.1dev
Summary: Footer Extra Info in invoices PDF
Home-page: https://github.com/sygel-technology/sy-account-financial-reporting
License: AGPL-3
Author: Sygel, Odoo Community Association (OCA)
Author-email: support@odoo-community.org
Classifier: Programming Language :: Python
Classifier: Framework :: Odoo
Classifier: Framework :: Odoo :: 16.0
Classifier: License :: OSI Approved :: GNU Affero General Public License v3
